{"availability": ["added_by_name", "is_pending", "license", "price", "latest_version", "date_of_latest_version", "principal_contact_name", "principal_contact_email", "official_website"], "capabilities": ["periodicity_0d", "periodicity_1_and_2d", "periodicity_3d", "constraints", "rigid_bodies", "restraints", "ensembles", "monte_carlo", "free_energy_methods", "advanced_sampling_methods", "rnemd", "analysis_tools", "building_tools", "implicit_solvent", "forcefield_types", "forcefields", "file_formats", "qm_mm"], "others": ["description", "long_description", "comments", "required_citation", "domain"], "performance": ["parallel", "gpu", "knl_optimized"], "software_engineering": ["source_code_link", "executables", "code_management", "continuous_integration", "number_of_tests", "languages", "compilers"], "support": ["support_line", "documentation", "number_of_tutorials", "wiki", "forum", "mail_list", "gui"]}